cdk_toolkit/__init__.py
cdk_toolkit/cicd/__init__.py
cdk_toolkit/cicd/codebuild.py
cdk_toolkit/cicd/codecommit.py
cdk_toolkit/cicd/codepipeline.py
cdk_toolkit/connection/__init__.py
cdk_toolkit/connection/vpc.py
cdk_toolkit/container/__init__.py
cdk_toolkit/container/ecr.py
cdk_toolkit/container/ecs.py
cdk_toolkit/container/eks.py
cdk_toolkit/container/ssm.py
cdk_toolkit/database/__init__.py
cdk_toolkit/database/dynamodb.py
cdk_toolkit/database/rds.py
cdk_toolkit/datalake/__init__.py
cdk_toolkit/datalake/lakeformation.py
cdk_toolkit/notebook/__init__.py
cdk_toolkit/notebook/sagemaker.py
cdk_toolkit/notification/__init__.py
cdk_toolkit/notification/pinpoint.py
cdk_toolkit/notification/sns.py
cdk_toolkit/permission/__init__.py
cdk_toolkit/permission/iam.py
cdk_toolkit/serverless/__init__.py
cdk_toolkit/serverless/serverless_lambda.py
cdk_toolkit/stacks/__init__.py
cdk_toolkit/stacks/cicd_stacks.py
cdk_toolkit/stacks/connection_stacks.py
cdk_toolkit/stacks/container_stacks.py
cdk_toolkit/stacks/datalake_stacks.py
cdk_toolkit/stacks/notification_stacks.py
cdk_toolkit/stacks/permission_stacks.py
cdk_toolkit/stacks/storage_stacks.py
cdk_toolkit/storage/__init__.py
cdk_toolkit/storage/infrastructure.py
cdk_toolkit-0.0.89.dist-info/LICENSE
cdk_toolkit-0.0.89.dist-info/METADATA
cdk_toolkit-0.0.89.dist-info/WHEEL
cdk_toolkit-0.0.89.dist-info/top_level.txt
cdk_toolkit-0.0.89.dist-info/RECORD
