Metadata-Version: 2.1
Name: cdk-toolkit
Version: 0.0.89
Summary: AWS Cloud Development Toolkit
Home-page: http://pypi.python.org/pypi/cdk-toolkit/
Author: Ryan Moos
Author-email: ryan@moos.engineering
License: LICENSE
Platform: UNKNOWN
License-File: LICENSE
Requires-Dist: aws-cdk-lib
Requires-Dist: boto3
Requires-Dist: pyopenssl
